qencode3/__init__.py
qencode3/client.py
qencode3/const.py
qencode3/custom_params.py
qencode3/exeptions.py
qencode3/httptools.py
qencode3/metadata.py
qencode3/task.py
qencode3/tools.py
qencode3/tus_uploader.py
qencode3/utils.py
qencode3-1.0.1.dist-info/LICENSE
qencode3-1.0.1.dist-info/METADATA
qencode3-1.0.1.dist-info/WHEEL
qencode3-1.0.1.dist-info/top_level.txt
qencode3-1.0.1.dist-info/RECORD
