Metadata-Version: 2.1
Name: qencode3
Version: 1.0.1
Summary: Qencode client library to easily setup a working solution using Python v3.x.
Home-page: https://github.com/qencode-dev/qencode-api-python3-client
Author: Qencode Developer
Author-email: team@qencode.com
License: proprietary
Keywords: qencode3,qencode.com,cloud.qencode.com
Platform: UNKNOWN
Classifier: Development Status :: 5 - Production/Stable
Classifier: Intended Audience :: Developers
Classifier: Topic :: Software Development :: Build Tools
Classifier: License :: Other/Proprietary License
Classifier: Programming Language :: Python :: 3.6
